cash/__init__.py
cash/config.py
cash/handlers.py
cash/main.py
cash/node.py
cash/nodeset.py
cash/utils.py
cascading_shell-1.2.dist-info/METADATA
cascading_shell-1.2.dist-info/WHEEL
cascading_shell-1.2.dist-info/entry_points.txt
cascading_shell-1.2.dist-info/top_level.txt
cascading_shell-1.2.dist-info/RECORD
