Metadata-Version: 2.1
Name: cascading-shell
Version: 1.2
Home-page: https://github.com/janoliver/cash
Author: Jan Oliver Oelerich
Author-email: janoliver@oelerich.org
License: GPL
Keywords: shell,hpc,computer cluster
Classifier: Environment :: Console
Classifier: Development Status :: 4 - Beta
Classifier: Intended Audience :: Science/Research
Classifier: Natural Language :: English
Classifier: Operating System :: Unix
Classifier: Programming Language :: Python :: 3.6
Classifier: Topic :: System :: Distributed Computing
Classifier: Topic :: System :: Shells
Classifier: Topic :: System :: Systems Administration
Classifier: Topic :: Utilities
Provides-Extra: colored_output
Requires-Dist: termcolor ; extra == 'colored_output'
